{
  "project_info": {
    "project_number": "67469739635",
    "firebase_url": "https://usipdtu-9de35.firebaseio.com",
    "project_id": "usipdtu-9de35",
    "storage_bucket": "usipdtu-9de35.appspot.com"
  },
  "client": [
    {
      "client_info": {
        "mobilesdk_app_id": "1:67469739635:android:a3a8b21d8d5f8e63",
        "android_client_info": {
          "package_name": "com.app.ayushmittal.usipdtu"
        }
      },
      "oauth_client": [
        {
          "client_id": "67469739635-0n2lutpaefa6b21glva9ssj7qen5vibr.apps.googleusercontent.com",
          "client_type": 1,
          "android_info": {
            "package_name": "com.app.ayushmittal.usipdtu",
            "certificate_hash": "863f6075e1a8d72027968050c7f82ec3a9f19454"
          }
        },
        {
          "client_id": "67469739635-tprjt2to29qa10i38avvm1vb2ktu6hoq.apps.googleusercontent.com",
          "client_type": 3
        }
      ],
      "api_key": [
        {
          "current_key": "AIzaSyCNgR_jafcwR8IHBYHr48l0aAZ-UZOvGmM"
        }
      ],
      "services": {
        "analytics_service": {
          "status": 1
        },
        "appinvite_service": {
          "status": 2,
          "other_platform_oauth_client": [
            {
              "client_id": "67469739635-tprjt2to29qa10i38avvm1vb2ktu6hoq.apps.googleusercontent.com",
              "client_type": 3
            }
          ]
        },
        "ads_service": {
          "status": 2
        }
      }
    }
  ],
  "configuration_version": "1"
}